dj_spinners/__init__.py
dj_spinners/apps.py
dj_spinners/assets/svg/12-dots-scale-rotate.svg
dj_spinners/assets/svg/180-ring-with-bg.svg
dj_spinners/assets/svg/180-ring.svg
dj_spinners/assets/svg/270-ring-with-bg.svg
dj_spinners/assets/svg/270-ring.svg
dj_spinners/assets/svg/3-dots-bounce.svg
dj_spinners/assets/svg/3-dots-fade.svg
dj_spinners/assets/svg/3-dots-move.svg
dj_spinners/assets/svg/3-dots-rotate.svg
dj_spinners/assets/svg/3-dots-scale-middle.svg
dj_spinners/assets/svg/3-dots-scale.svg
dj_spinners/assets/svg/4-dots-gooey.svg
dj_spinners/assets/svg/4-dots-rotate.svg
dj_spinners/assets/svg/6-dots-rotate.svg
dj_spinners/assets/svg/6-dots-scale-middle.svg
dj_spinners/assets/svg/6-dots-scale.svg
dj_spinners/assets/svg/8-dots-rotate-scale.svg
dj_spinners/assets/svg/8-dots-rotate.svg
dj_spinners/assets/svg/90-ring-with-bg.svg
dj_spinners/assets/svg/90-ring-with-gradient.svg
dj_spinners/assets/svg/90-ring.svg
dj_spinners/assets/svg/audio.svg
dj_spinners/assets/svg/ball-triangle.svg
dj_spinners/assets/svg/bars-fade.svg
dj_spinners/assets/svg/bars-rotate-fade.svg
dj_spinners/assets/svg/bars-scale-fade.svg
dj_spinners/assets/svg/bars-scale-middle.svg
dj_spinners/assets/svg/bars-scale.svg
dj_spinners/assets/svg/bars.svg
dj_spinners/assets/svg/blocks-scale.svg
dj_spinners/assets/svg/blocks-shuffle-2.svg
dj_spinners/assets/svg/blocks-shuffle-3.svg
dj_spinners/assets/svg/blocks-shuffle-4.svg
dj_spinners/assets/svg/blocks-shuffle-5.svg
dj_spinners/assets/svg/blocks-wave.svg
dj_spinners/assets/svg/bouncing-ball.svg
dj_spinners/assets/svg/circle-fade.svg
dj_spinners/assets/svg/circles.svg
dj_spinners/assets/svg/clock.svg
dj_spinners/assets/svg/cog01.svg
dj_spinners/assets/svg/cog02.svg
dj_spinners/assets/svg/cog03.svg
dj_spinners/assets/svg/cog04.svg
dj_spinners/assets/svg/cog05.svg
dj_spinners/assets/svg/cog06.svg
dj_spinners/assets/svg/cog07.svg
dj_spinners/assets/svg/cog08.svg
dj_spinners/assets/svg/cog09.svg
dj_spinners/assets/svg/cog10.svg
dj_spinners-0.3.1.dist-info/WHEEL
dj_spinners-0.3.1.dist-info/METADATA
dj_spinners-0.3.1.dist-info/RECORD
