Metadata-Version: 2.3
Name: dj-spinners
Version: 0.3.1
Summary: Pure SVG loading spinners for Django.
Keywords: django,spinners,svg
Author: Adam Hill
Author-email: Adam Hill <adam@adamghill.com>
License: MIT
Classifier: Development Status :: 3 - Alpha
Classifier: Framework :: Django
Classifier: Framework :: Django :: 3.2
Classifier: Framework :: Django :: 4.0
Classifier: Framework :: Django :: 4.1
Classifier: Framework :: Django :: 4.2
Classifier: Intended Audience :: Developers
Classifier: License :: OSI Approved :: MIT License
Classifier: Programming Language :: Python :: 3.10
Classifier: Programming Language :: Python :: 3.11
Classifier: Programming Language :: Python :: 3.12
Classifier: Programming Language :: Python :: 3.13
Classifier: Topic :: Software Development :: Libraries :: Python Modules
Requires-Dist: django
Requires-Python: >=3.10
Project-URL: homepage, https://github.com/adamghill/dj-spinners/
Project-URL: repository, https://github.com/adamghill/dj-spinners.git
